LICENSE
MANIFEST.in
README.md
RELEASE-VERSION
setup.py
version.py
dossier/__init__.py
dossier.fc.egg-info/PKG-INFO
dossier.fc.egg-info/SOURCES.txt
dossier.fc.egg-info/dependency_links.txt
dossier.fc.egg-info/entry_points.txt
dossier.fc.egg-info/namespace_packages.txt
dossier.fc.egg-info/not-zip-safe
dossier.fc.egg-info/requires.txt
dossier.fc.egg-info/top_level.txt
dossier/fc/__init__.py
dossier/fc/dump.py
dossier/fc/exceptions.py
dossier/fc/feature_collection.py
dossier/fc/feature_tokens.py
dossier/fc/geocoords.py
dossier/fc/string_counter.py
dossier/fc/vector.py
dossier/fc/tests/__init__.py
dossier/fc/tests/performance.py
dossier/fc/tests/run.py
dossier/fc/tests/test_chunk.py
dossier/fc/tests/test_counter.py
dossier/fc/tests/test_feature_collection.py
dossier/fc/tests/test_feature_tokens.py
dossier/fc/tests/test_generation.py
dossier/fc/tests/test_geocoords.py
dossier/fc/tests/test_read_only.py
dossier/fc/tests/test_registry.py
dossier/fc/tests/test_serialization.py
dossier/fc/tests/test_truncation.py
dossier/fc/tests/thing.py