Metadata-Version: 1.1
Name: dossier.fc
Version: 0.3.5
Summary: Feature collections for DossierStack
Home-page: http://github.com/dossier/dossier.fc
Author: Diffeo, Inc.
Author-email: support@diffeo.com
License: MIT/X11 license http://opensource.org/licenses/MIT
Platform: UNKNOWN
Classifier: Development Status :: 3 - Alpha
Classifier: Topic :: Utilities
Classifier: License :: OSI Approved :: MIT License
